pco_tools/__init__.py
pco_tools/pco_reader.py
pco_tools-1.0.0.dist-info/DESCRIPTION.rst
pco_tools-1.0.0.dist-info/METADATA
pco_tools-1.0.0.dist-info/RECORD
pco_tools-1.0.0.dist-info/WHEEL
pco_tools-1.0.0.dist-info/metadata.json
pco_tools-1.0.0.dist-info/top_level.txt
